codeatlas/__init__.py
codeatlas/analyzer.py
codeatlas/cli.py
codeatlas/graph_builder.py
codeatlas/main.py
codeatlas/visualizer.py
codeatlas-0.1.0.dist-info/METADATA
codeatlas-0.1.0.dist-info/WHEEL
codeatlas-0.1.0.dist-info/entry_points.txt
codeatlas-0.1.0.dist-info/top_level.txt
codeatlas-0.1.0.dist-info/RECORD
