Metadata-Version: 2.4
Name: codeatlas
Version: 0.1.0
Summary: A Python library for visualizing and understanding codebases.
Home-page: https://github.com/rahulbedjavalge/codeatlas
Author: Rahul Bedjavalge
Author-email: rahulinberlinn@gmail.com
Classifier: Programming Language :: Python :: 3
Classifier: License :: OSI Approved :: MIT License
Classifier: Operating System :: OS Independent
Requires-Python: >=3.6
Requires-Dist: flask
Requires-Dist: networkx
Requires-Dist: click
Dynamic: author
Dynamic: author-email
Dynamic: classifier
Dynamic: description
Dynamic: description-content-type
Dynamic: home-page
Dynamic: requires-dist
Dynamic: requires-python
Dynamic: summary
